{
"type": "FeatureCollection",
"name": "geo_02_特定施設入居者生活介護（有料老人ホーム（サービス付き高齢者向け住宅））",
"crs": { "type": "name", "properties": { "name": "urn:ogc:def:crs:OGC:1.3:CRS84" } },
"features": [
{ "type": "Feature", "properties": { "内容": "サービス付高齢者住宅リゾート「きずな」【特定施設入居者生活介護（有料老人ホーム（サービス付き高齢者向け住宅））】青森県十和田市大字三本木字一本木沢19-1", "url": "https://www.kaigokensaku.mhlw.go.jp/02/index.php?action_kouhyou_detail_004_kani=true&JigyosyoCd=0270601198-00&ServiceCd=&Type=search", "url2": "https://echo-aomori.jp/welfare/" }, "geometry": { "type": "Point", "coordinates": [ 141.234466486508126, 40.641018929619136 ] } },
{ "type": "Feature", "properties": { "内容": "シニアライフ大津【特定施設入居者生活介護（有料老人ホーム（サービス付き高齢者向け住宅））】青森県三沢市大津二丁目１２－３７４", "url": "https://www.kaigokensaku.mhlw.go.jp/02/index.php?action_kouhyou_detail_004_kani=true&JigyosyoCd=0270700610-00&ServiceCd=&Type=search", "url2": "http://www.rakuseikai.or.jp/" }, "geometry": { "type": "Point", "coordinates": [ 141.41960210000002, 40.6823849 ] } },
{ "type": "Feature", "properties": { "内容": "サービス付き高齢者向け住宅　双松苑【特定施設入居者生活介護（有料老人ホーム（サービス付き高齢者向け住宅））】青森県三戸郡階上町大字角柄折字餅粟久保４番地１", "url": "https://www.kaigokensaku.mhlw.go.jp/02/index.php?action_kouhyou_detail_004_kani=true&JigyosyoCd=0272701608-00&ServiceCd=&Type=search", "url2": null }, "geometry": { "type": "Point", "coordinates": [ 141.57445359999997, 40.4392704 ] } }
]
}
